xivapy/__init__.py
xivapy/client.py
xivapy/exceptions.py
xivapy/model.py
xivapy/model.pyi
xivapy/py.typed
xivapy/query.py
xivapy/types.py
xivapy/version.py
xivapy-0.5.0.dist-info/METADATA
xivapy-0.5.0.dist-info/WHEEL
xivapy-0.5.0.dist-info/licenses/LICENSE
xivapy-0.5.0.dist-info/RECORD
