Metadata-Version: 2.4
Name: xivapy
Version: 0.5.0
Summary: Async Python client for XIVAPI for Final Fantasy XIV
Project-URL: Homepage, https://github.com/macrocosmos-app/xivapy
Project-URL: Repository, https://github.com/macrocosmos-app/xivapy
Project-URL: Issues, https://github.com/macrocosmos-app/xivapy/issues
Project-URL: Documentation, https://github.com/macrocosmos-app/xivapy#readme
Author-email: Oowazu Nonowazu <oowazu.nonowazu@gmail.com>
License: MIT
License-File: LICENSE
Keywords: api,async,ffxiv,xiv,xivapi
Classifier: Development Status :: 3 - Alpha
Classifier: Framework :: AsyncIO
Classifier: License :: OSI Approved :: MIT License
Classifier: Programming Language :: Python :: 3
Classifier: Programming Language :: Python :: 3.13
Classifier: Topic :: Games/Entertainment
Requires-Python: >=3.13.2
Requires-Dist: aiostream>=0.7.0
Requires-Dist: httpx>=0.28.1
Requires-Dist: pydantic>=2.11.7
